pandas2pgfplots/__init__.py
pandas2pgfplots/display.py
pandas2pgfplots/plots.py
pandas2pgfplots/utils.py
pandas2pgfplots-0.2.0.dist-info/LICENSE
pandas2pgfplots-0.2.0.dist-info/METADATA
pandas2pgfplots-0.2.0.dist-info/WHEEL
pandas2pgfplots-0.2.0.dist-info/top_level.txt
pandas2pgfplots-0.2.0.dist-info/RECORD
