Metadata-Version: 2.1
Name: pandas2pgfplots
Version: 0.2.0
Summary: Library for pgfplots plots from pandas DataFrames
Home-page: https://github.com/xblahoud/pandas2pgfplots
Author: Fanda Blahoudek
Author-email: fandikb+dev@gmail.com
License: MIT
Platform: UNKNOWN
Classifier: License :: OSI Approved :: MIT License
Classifier: Programming Language :: Python :: 3
Classifier: Programming Language :: Python :: 3.6
Requires-Python: >=3.6.0
Requires-Dist: itikz (>=0.1.5)
Requires-Dist: pandas (>=1.0)
